pymde/__init__.py
pymde/average_distortion.py
pymde/benchmark.py
pymde/constraints.py
pymde/datasets.py
pymde/experiment_utils.py
pymde/lbfgs.py
pymde/optim.py
pymde/problem.py
pymde/quadratic.py
pymde/recipes.py
pymde/test_optim.py
pymde/test_quadratic.py
pymde/test_recipes.py
pymde/test_util.py
pymde/testing.py
pymde/util.py
pymde/functions/__init__.py
pymde/functions/function.py
pymde/functions/losses.py
pymde/functions/penalties.py
pymde/preprocess/__init__.py
pymde/preprocess/_graph.cp312-win_amd64.pyd
pymde/preprocess/data_matrix.py
pymde/preprocess/generic.py
pymde/preprocess/graph.py
pymde/preprocess/preprocess.py
pymde/preprocess/test_data_matrix.py
pymde/preprocess/test_graph.py
pymde-0.2.3.dist-info/licenses/LICENSE
pymde-0.2.3.dist-info/METADATA
pymde-0.2.3.dist-info/WHEEL
pymde-0.2.3.dist-info/top_level.txt
pymde-0.2.3.dist-info/RECORD
