Metadata-Version: 2.4
Name: pymde
Version: 0.2.3
Summary: Minimum-Distortion Embedding
Home-page: https://github.com/cvxgrp/pymde
Author: Akshay Agrawal
Author-email: akshayka@cs.stanford.edu
License: Apache License, Version 2.0
Classifier: Programming Language :: Python :: 3
License-File: LICENSE
Requires-Dist: matplotlib
Requires-Dist: numpy>=2.0
Requires-Dist: pynndescent>=0.5
Requires-Dist: numba>=0.59.0
Requires-Dist: scipy
Requires-Dist: torch>=1.7.1
Requires-Dist: torchvision>=0.8.2
Requires-Dist: requests
Dynamic: author
Dynamic: author-email
Dynamic: classifier
Dynamic: description
Dynamic: description-content-type
Dynamic: home-page
Dynamic: license
Dynamic: license-file
Dynamic: requires-dist
Dynamic: summary
